hkserror/__init__.py
hkserror/hkserror.py
hkserror/version.py
hkserror-0.0.2.dist-info/LICENSE
hkserror-0.0.2.dist-info/METADATA
hkserror-0.0.2.dist-info/WHEEL
hkserror-0.0.2.dist-info/top_level.txt
hkserror-0.0.2.dist-info/RECORD
